LICENSE.txt
MANIFEST.in
README.txt
requirements.txt
setup.py
tox.ini
django_Harman/__init__.py
django_Harman/admin.py
django_Harman/apps.py
django_Harman/models.py
django_Harman/views.py
django_Harman.egg-info/PKG-INFO
django_Harman.egg-info/SOURCES.txt
django_Harman.egg-info/dependency_links.txt
django_Harman.egg-info/not-zip-safe
django_Harman.egg-info/requires.txt
django_Harman.egg-info/top_level.txt
docs/01-testing.rst
docs/Makefile
docs/conf.py
docs/index.rst
docs/make.bat
tests/__init__.py
tests/asgi.py
tests/runtests.py
tests/settings.py
tests/urls.py
tests/wsgi.py