Metadata-Version: 1.1
Name: django-Harman
Version: 1.1.0
Summary: Super awesome portable module for Django
Home-page: https://github.com/harmannkibue/Django_harmanModule
Author: Harman Kibue
Author-email: harmannkibue@gmail.com
License: MIT License
Download-URL: https://github.com/harmannkibue/Django_harmanModule.git
Platform: UNKNOWN
Classifier: Operating System :: OS Independent
Classifier: Development Status :: 3 - Alpha
Classifier: Environment :: Web Environment
Classifier: Framework :: Django
Classifier: Intended Audience :: Developers
Classifier: License :: OSI Approved :: MIT License
Classifier: Programming Language :: Python :: 2
Classifier: Programming Language :: Python :: 3
Classifier: Topic :: Software Development :: Libraries :: Python Modules
